getSourceCode/__init__.py
getSourceCode/check.py
getSourceCode/common.py
getSourceCode/config.py
getSourceCode/filter.py
getSourceCode/handle.py
getSourceCode/keys.py
getSourceCode/menu.py
getSourceCode-2.0.8.dist-info/LICENSE
getSourceCode-2.0.8.dist-info/METADATA
getSourceCode-2.0.8.dist-info/WHEEL
getSourceCode-2.0.8.dist-info/entry_points.txt
getSourceCode-2.0.8.dist-info/top_level.txt
getSourceCode-2.0.8.dist-info/RECORD
