Metadata-Version: 2.1
Name: getSourceCode
Version: 2.0.8
Summary: Simple way to get contract source code verified on blockchain explorer.
Home-page: https://github.com/5hawnXu/getSourceCode
Author: Shawn Xu
Author-email: support@hxzy.me
License: UNKNOWN
Platform: UNKNOWN
License-File: LICENSE
Requires-Dist: retrying
